{
    "swagger": "2.0",
    "info": {
        "description": "Your API description",
        "title": "Your API Title",
        "termsOfService": "http://example.com/terms/",
        "contact": {},
        "version": "1.0"
    },
    "host": "localhost:8080",
    "basePath": "/api/v1",
    "paths": {
        "/example/helloworld": {
            "get": {
                "description": "do ping",
                "consumes": [
                    "application/json"
                ],
                "produces": [
                    "application/json"
                ],
                "tags": [
                    "example"
                ],
                "summary": "ping example",
                "responses": {
                    "200": {
                        "description": "OK",
                        "schema": {
                            "type": "string"
                        }
                    }
                }
            }
        }
    }
}